scrap_utils/__init__.py
scrap_utils/scrap_utils.py
scrap_utils-0.0.2.dist-info/LICENSE.txt
scrap_utils-0.0.2.dist-info/METADATA
scrap_utils-0.0.2.dist-info/WHEEL
scrap_utils-0.0.2.dist-info/top_level.txt
scrap_utils-0.0.2.dist-info/RECORD
