Metadata-Version: 2.1
Name: scrap-utils
Version: 0.0.2
Summary: A small package that contains commonly used codes while scraping
Home-page: https://github.com/bizzyvinci/scrap-utils
Author: Bisola Olasehinde
Author-email: horlasehinde@gmail.com
License: MIT
Keywords: scrap,scraping,scraper,requests,csv,json
Platform: UNKNOWN
Classifier: Programming Language :: Python :: 3
Classifier: License :: OSI Approved :: MIT License
Classifier: Operating System :: OS Independent
Requires-Python: >=3.6
Requires-Dist: requests
